{"add_friend":[{"friend_link":"https://www.shimail.cn","friend_name":"皓月星际"},{"friend_link":"https://www.wsp.im","friend_name":"回忆录"}],"add_home_adv":[],"author":"秋溟","description":"","icp":"","is_friends":true,"is_home_adv":false,"is_mp":false,"is_reward":false,"is_sitename":true,"is_sns":true,"logo":"","media_platform":"","security":"","security_url":"","sns_bilibili":"","sns_csdn":"","sns_douban":"","sns_facebook":"","sns_github":"https://github.com/wsp03","sns_jianshu":"","sns_juejin":"","sns_qq":"","sns_sf":"","sns_toutiao":"","sns_twitter":"","sns_wechat":"","sns_weibo":"","sns_zhihu":"","weixin_reward":"","zhifubao_reward":""}
